{
  "__inputs": [
    {
      "name": "DS_INFLUXDB",
      "label": "InfluxDB",
      "description": "",
      "type": "datasource",
      "pluginId": "influxdb",
      "pluginName": "InfluxDB"
    }
  ],
  "__requires": [
    {
      "type": "grafana",
      "id": "grafana",
      "name": "Grafana",
      "version": "6.5.3"
    },
    {
      "type": "panel",
      "id": "graph",
      "name": "Graph",
      "version": ""
    },
    {
      "type": "datasource",
      "id": "influxdb",
      "name": "InfluxDB",
      "version": "1.0.0"
    }
  ],
  "annotations": {
    "list": [
      {
        "builtIn": 1,
        "datasource": "-- Grafana --",
        "enable": true,
        "hide": true,
        "iconColor": "rgba(0, 211, 255, 1)",
        "name": "Annotations & Alerts",
        "type": "dashboard"
      }
    ]
  },
  "editable": true,
  "gnetId": null,
  "graphTooltip": 0,
  "id": null,
  "links": [],
  "panels": [
    {
      "aliasColors": {
        "Upload Bandwidth": "blue"
      },
      "bars": false,
      "dashLength": 10,
      "dashes": false,
      "datasource": "${DS_INFLUXDB}",
      "decimals": 2,
      "fill": 1,
      "fillGradient": 0,
      "gridPos": {
        "h": 19,
        "w": 24,
        "x": 0,
        "y": 0
      },
      "hiddenSeries": false,
      "id": 2,
      "legend": {
        "alignAsTable": true,
        "avg": true,
        "current": true,
        "max": false,
        "min": true,
        "rightSide": false,
        "show": true,
        "total": false,
        "values": true
      },
      "lines": true,
      "linewidth": 1,
      "nullPointMode": "null",
      "options": {
        "dataLinks": []
      },
      "percentage": false,
      "pointradius": 2,
      "points": false,
      "renderer": "flot",
      "seriesOverrides": [],
      "spaceLength": 10,
      "stack": false,
      "steppedLine": false,
      "targets": [
        {
          "alias": "Download Bandwidth",
          "groupBy": [],
          "measurement": "download",
          "orderByTime": "ASC",
          "policy": "default",
          "refId": "A",
          "resultFormat": "time_series",
          "select": [
            [
              {
                "params": [
                  "bandwidth"
                ],
                "type": "field"
              }
            ]
          ],
          "tags": []
        },
        {
          "alias": "Upload Bandwidth",
          "groupBy": [],
          "measurement": "upload",
          "orderByTime": "ASC",
          "policy": "default",
          "refId": "B",
          "resultFormat": "time_series",
          "select": [
            [
              {
                "params": [
                  "bandwidth"
                ],
                "type": "field"
              }
            ]
          ],
          "tags": []
        }
      ],
      "thresholds": [],
      "timeFrom": null,
      "timeRegions": [],
      "timeShift": null,
      "title": "Bandwidth Trend",
      "tooltip": {
        "shared": true,
        "sort": 0,
        "value_type": "individual"
      },
      "type": "graph",
      "xaxis": {
        "buckets": null,
        "mode": "time",
        "name": null,
        "show": true,
        "values": []
      },
      "yaxes": [
        {
          "decimals": null,
          "format": "Mbits",
          "label": "",
          "logBase": 1,
          "max": "120",
          "min": "0",
          "show": true
        },
        {
          "format": "short",
          "label": null,
          "logBase": 1,
          "max": null,
          "min": null,
          "show": true
        }
      ],
      "yaxis": {
        "align": false,
        "alignLevel": null
      }
    }
  ],
  "schemaVersion": 21,
  "style": "dark",
  "tags": [],
  "templating": {
    "list": []
  },
  "time": {
    "from": "now-5m",
    "to": "now"
  },
  "timepicker": {},
  "timezone": "",
  "title": "SpeedTest",
  "uid": "_ZAK3MVGk",
  "version": 1
}